cacheyou-23.3.dist-info/METADATA
cacheyou-23.3.dist-info/WHEEL
cacheyou-23.3.dist-info/entry_points.txt
cacheyou-23.3.dist-info/licenses/LICENSE.txt
cacheyou/__init__.py
cacheyou/_cmd.py
cacheyou/adapter.py
cacheyou/cache.py
cacheyou/caches/__init__.py
cacheyou/caches/file_cache.py
cacheyou/caches/redis_cache.py
cacheyou/controller.py
cacheyou/filewrapper.py
cacheyou/heuristics.py
cacheyou/py.typed
cacheyou/serialize.py
cacheyou/wrapper.py
cacheyou-23.3.dist-info/RECORD
